openlogprobs/__init__.py
openlogprobs/extract.py
openlogprobs/models.py
openlogprobs/utils.py
openlogprobs-0.0.1.dist-info/METADATA
openlogprobs-0.0.1.dist-info/WHEEL
openlogprobs-0.0.1.dist-info/top_level.txt
openlogprobs-0.0.1.dist-info/RECORD
