Metadata-Version: 2.1
Name: openlogprobs
Version: 0.0.1
Summary: extract log-probabilities from APIs
Home-page: UNKNOWN
Author: Justin Chiu & Jack Morris
Author-email: jtc257@cornell.edu
License: UNKNOWN
Platform: UNKNOWN
Requires-Dist: numpy
Requires-Dist: openai
Requires-Dist: scipy
Requires-Dist: transformers
